pytedea/CNLS.py
pytedea/CNLSDDF.py
pytedea/DDF.py
pytedea/DDFDUAL.py
pytedea/DDFt.py
pytedea/DEA.py
pytedea/DEAt.py
pytedea/HYPER.py
pytedea/HYPERt.py
pytedea/MB.py
pytedea/MQDDF.py
pytedea/MQDDFt.py
pytedea/MQDEA.py
pytedea/MQDEAt.py
pytedea/MQNDDF.py
pytedea/NDDF.py
pytedea/NDDFDUAL.py
pytedea/StoNED.py
pytedea/__init__.py
pytedea/constant.py
pytedea/pytedea.py
pytedea/weakCNLSDDF.py
pytedea/weakCNLSNDDF.py
pytedea/weakCNLSNDDF_notransfer.py
pytedea/weakCNLSb.py
pytedea/weakCNLSx.py
pytedea/weakCNLSy.py
pytedea/weakMetaCNLSDDF.py
pytedea/weakMetaCNLSNDDF.py
pytedea/weakMetaCNLSb.py
pytedea/utils/CNLSDDFG1.py
pytedea/utils/CNLSDDFG2.py
pytedea/utils/CNLSDDFZG1.py
pytedea/utils/CNLSDDFZG2.py
pytedea/utils/CNLSG1.py
pytedea/utils/CNLSG2.py
pytedea/utils/CNLSZG1.py
pytedea/utils/CNLSZG2.py
pytedea/utils/CQERDDFG1.py
pytedea/utils/CQERDDFG2.py
pytedea/utils/CQERDDFZG1.py
pytedea/utils/CQERDDFZG2.py
pytedea/utils/CQERG1.py
pytedea/utils/CQERG2.py
pytedea/utils/CQERZG1.py
pytedea/utils/CQERZG2.py
pytedea/utils/MB_.py
pytedea/utils/__init__.py
pytedea/utils/interpolation.py
pytedea/utils/sweet.py
pytedea/utils/tools.py
pytedea/utils/weakCNLSDDFG1.py
pytedea/utils/weakCNLSDDFG2.py
pytedea/utils/weakCNLSDDFZG1.py
pytedea/utils/weakCNLSDDFZG2.py
pytedea/utils/weakCNLSG1.py
pytedea/utils/weakCNLSG2.py
pytedea/utils/weakCNLSZG1.py
pytedea/utils/weakCNLSZG2.py
pytedea/utils/weakCNLSbG1.py
pytedea/utils/weakCNLSbG2.py
pytedea/utils/weakCNLSbZG1.py
pytedea/utils/weakCNLSbZG2.py
pytedea/utils/weakCNLSxG1.py
pytedea/utils/weakCNLSxG2.py
pytedea/utils/weakCNLSxZG1.py
pytedea/utils/weakCNLSxZG2.py
pytedea/utils/weakCQERDDFG1.py
pytedea/utils/weakCQERDDFG2.py
pytedea/utils/weakCQERDDFZG1.py
pytedea/utils/weakCQERDDFZG2.py
pytedea/utils/weakCQERG1.py
pytedea/utils/weakCQERG2.py
pytedea/utils/weakCQERZG1.py
pytedea/utils/weakCQERZG2.py
pytedea/utils/weakCQERbG1.py
pytedea/utils/weakCQERbG2.py
pytedea/utils/weakCQERbZG1.py
pytedea/utils/weakCQERbZG2.py
pytedea/utils/weakCQERxG1.py
pytedea-0.0.7.dist-info/LICENSE
pytedea-0.0.7.dist-info/METADATA
pytedea-0.0.7.dist-info/WHEEL
pytedea-0.0.7.dist-info/dependency_links.txt
pytedea-0.0.7.dist-info/top_level.txt
pytedea-0.0.7.dist-info/RECORD
