Metadata-Version: 2.1
Name: pytedea
Version: 0.0.7
Summary: Data envelopment analysis using Python.
Home-page: https://github.com/advancehs/pytedea
Author: advancehs
Author-email: 1019753743@qq.com
License: GNU General Public License v3
Keywords: pytedea
Classifier: Intended Audience :: Developers
Classifier: License :: OSI Approved :: GNU General Public License v3 (GPLv3)
Classifier: Natural Language :: English
Classifier: Programming Language :: Python :: 3
Classifier: Programming Language :: Python :: 3.8
Classifier: Programming Language :: Python :: 3.9
Classifier: Programming Language :: Python :: 3.10
Classifier: Programming Language :: Python :: 3.11
Requires-Python: >=3.8
License-File: LICENSE
Requires-Dist: pyomo (>=6.4.4)
Requires-Dist: pandas (>=1.1.3)
Requires-Dist: numpy (>=1.19.2)
Requires-Dist: scipy (>=1.5.2)
Requires-Dist: matplotlib (>=3.5.1)
Requires-Dist: mosek (>=9.3.18)
